{
  "clearSelection": "Zrušit výběr",
  "exportCSV": "Exportovat do CSV",
  "filter": "Filtr: {{title}}",
  "filters": "Filtry",
  "hideField": "Skrýt pole",
  "more": "Více",
  "selectAll": "Vybrat vše",
  "share": "Sdílet",
  "showSelected": "Zobrazit vybrané",
  "switchSelected": "Přepnout vybrané",
  "zoom": "Přiblížení",
  "editMultiple": "Ř_Edit multiple______________ů",
  "fetchingData": "Načítání dat",
  "refresh": "Obnovit",
  "showAll": "Zobrazit vše",
  "recordsSelected": "Celkem: {{total}} | Výběr: {{selected}}",
  "moreOptions": "Další možnosti tabulky",
  "showHideColumns": "Zobrazit/skrýt sloupce",
  "searchPlaceholder": "Ř_Search text in {{fields}} field_________________ů"
}
