{
  "clearSelection": "Izbriši izbor",
  "exportCSV": "Izvezi u CSV",
  "filter": "Filter: {{title}}",
  "filters": "Filteri",
  "hideField": "Sakrij polje",
  "more": "Više",
  "selectAll": "Izaberi sve",
  "share": "Podeli",
  "showSelected": "Pokaži selektovano",
  "switchSelected": "Prebaci izabrano",
  "zoom": "Zumiranje",
  "editMultiple": "Č_Edit multiple______________ž",
  "fetchingData": "Preuzimanje podataka",
  "refresh": "Osveži",
  "showAll": "Prikaži sve",
  "recordsSelected": "Ukupno: {{total}} | Odabir: {{selected}}",
  "moreOptions": "Više opcija za tabelu",
  "showHideColumns": "Prikaži/sakrij kolone",
  "searchPlaceholder": "Č_Search text in {{fields}} field_________________ž"
}
