{
  "createReportHeader": "Stvori izvješće",
  "share": "Podijeli",
  "sort": "Sortiraj",
  "filter": "Filtriraj",
  "expand": "Proširi",
  "collapse": "Sažmi",
  "next": "Sljedeće",
  "submit": "Podnesi",
  "cancel": "Odustani",
  "back": "Natrag",
  "error": "Pogreška",
  "invalidConfigurationErrorMsg": "Nevaljana konfiguracija",
  "noLayerToDisplayErrorMsg": "Konfigurirana web-karta nema nijedan sloj geoobjekta koji se može uređivati.",
  "chooseCategoryMsg": "Choose a category for your report.",
  "featureErrorMsg": "Geoobjekti nisu pronađeni.",
  "featureEditFormInfoMsg": "Please provide the details for your report.",
  "currentLocationMsg": "Iskoristi moju trenutačnu lokaciju",
  "addLocationMsg": "Add the location for your report.",
  "reportSubmit": "Izvješće je podneseno.",
  "submitMsg": "Hvala vam! Vaše je izvješće uspješno poslano."
}
