{
  "createReportHeader": "Vytvořit zprávu",
  "share": "Sdílet",
  "sort": "Seřadit",
  "filter": "Filtr",
  "expand": "Rozbalit",
  "collapse": "Sbalit",
  "next": "Další",
  "submit": "Odeslat",
  "cancel": "Storno",
  "back": "Zpět",
  "error": "Chyba",
  "invalidConfigurationErrorMsg": "Neplatná konfigurace",
  "noLayerToDisplayErrorMsg": "Nakonfigurovaná webová mapa nemá žádnou vrstvu prvků, kterou lze editovat.",
  "chooseCategoryMsg": "Choose a category for your report.",
  "featureErrorMsg": "Prvky nenalezeny.",
  "featureEditFormInfoMsg": "Please provide the details for your report.",
  "currentLocationMsg": "Použijte mou aktuální polohu",
  "addLocationMsg": "Add the location for your report.",
  "reportSubmit": "Zpráva odeslána",
  "submitMsg": "Děkujeme! Váš report byl úspěšně odeslán."
}
