{
  "listName": "Ім'я списку",
  "listNamePlaceholder": "Введіть ім'я тут",
  "searchDistance": "Відстань пошуку",
  "select": "Шар",
  "selectedFeatures": "{{n}} об'єкти(-ів) вибрано",
  "selectionLoading": "Завантаження вибору",
  "sketch": "Скетч",
  "bufferLayer": "Буферний шар",
  "sketchLayer": "Шар скетчу",
  "useLayerFeatures": "Використовувати об’єкти шару",
  "inputLayer": "Вхідний шар",
  "useLayerFeaturesTooltip": "Виберіть шар і за допомогою інструментів «Скетч» вкажіть об’єкти, які можна використовувати як кордони для вибору об’єктів, які перетинаються із вхідного шару.",
  "useSearchDistanceTootip": "Визначте відстань для буфера пошуку, який вибиратиме вхідні об’єкти, які перетинають буфер.",
  "placeholder": "Знайти адресу або місце"
}
