{
    "add": "Add",
    "addTitle": "Add title",
    "cancel": "Cancel",
    "csv": "CSV",
    "done": "Done",
    "downloadNoLists": "There are no lists to export. Go to My lists to create a list of features.",
    "export": "Export",
    "exportCSV": "Export CSV",
    "exportPDF": "Export PDF",
    "exportTip": "Export tip",
    "includeMap": "Include map",
    "listHasSetsTip": "Edit or delete existing lists or choose a layer and click Add to create a notification list.",
    "myLists": "My lists",
    "numDuplicates": "There are {{n}} duplicates",
    "pdf": "PDF",
    "removeDuplicate": "Remove duplicate addresses",
    "selectedFeatures": "{{n}} selected features",
    "selectLayerAndAdd": "Choose a layer, click Add, and select features to create a list that you can export to CSV or PDF for download.",
    "selectPDFLabelOption": "Select PDF label option",
    "selectSearchTip": "Search for an address, place, or feature to make a selection.",
    "stepTwoFull": "Select features from: {{layer}}",
    "title": "Title",
    "titlePlaceholder": ""
}
